re_common/__init__.py
re_common/baselibrary/__init__.py
re_common/baselibrary/baseabs/__init__.py
re_common/baselibrary/baseabs/baseabs.py
re_common/baselibrary/database/__init__.py
re_common/baselibrary/database/mbuilder.py
re_common/baselibrary/database/moudle.py
re_common/baselibrary/database/msqlite3.py
re_common/baselibrary/database/mysql.py
re_common/baselibrary/database/sql_factory.py
re_common/baselibrary/mthread/MThreadingRun.py
re_common/baselibrary/mthread/MThreadingRunEvent.py
re_common/baselibrary/mthread/__init__.py
re_common/baselibrary/mthread/mythreading.py
re_common/baselibrary/pakge_other/__init__.py
re_common/baselibrary/pakge_other/socks.py
re_common/baselibrary/readconfig/__init__.py
re_common/baselibrary/readconfig/config_factory.py
re_common/baselibrary/readconfig/ini_config.py
re_common/baselibrary/readconfig/toml_config.py
re_common/baselibrary/temporary/__init__.py
re_common/baselibrary/temporary/envdata.py
re_common/baselibrary/tools/__init__.py
re_common/baselibrary/tools/contrast_db3.py
re_common/baselibrary/tools/copy_file.py
re_common/baselibrary/tools/db3_2_sizedb3.py
re_common/baselibrary/tools/foreachgz.py
re_common/baselibrary/tools/get_attr.py
re_common/baselibrary/tools/image_to_pdf.py
re_common/baselibrary/tools/java_code_deal.py
re_common/baselibrary/tools/javacode.py
re_common/baselibrary/tools/mdb_db3.py
re_common/baselibrary/tools/merge_file.py
re_common/baselibrary/tools/merge_gz_file.py
re_common/baselibrary/tools/mongo_tools.py
re_common/baselibrary/tools/move_file.py
re_common/baselibrary/tools/myparsel.py
re_common/baselibrary/tools/rename_dir_file.py
re_common/baselibrary/tools/sequoiadb_utils.py
re_common/baselibrary/tools/split_line_to_many.py
re_common/baselibrary/tools/stringtodicts.py
re_common/baselibrary/tools/workwechant_bot.py
re_common/baselibrary/tools/all_requests/__init__.py
re_common/baselibrary/tools/all_requests/aiohttp_request.py
re_common/baselibrary/tools/all_requests/httpx_requet.py
re_common-10.0.43.dist-info/licenses/LICENSE
re_common-10.0.43.dist-info/METADATA
re_common-10.0.43.dist-info/WHEEL
re_common-10.0.43.dist-info/top_level.txt
re_common-10.0.43.dist-info/RECORD
