Metadata-Version: 2.4
Name: re_common
Version: 10.0.43
Summary: a library about all python projects
Home-page: https://gitee.com/xujiangios/re-common
Author: vic
Author-email: xujiang5@163.com
Classifier: Programming Language :: Python :: 3
Classifier: Development Status :: 2 - Pre-Alpha
Classifier: Operating System :: OS Independent
Requires-Python: >=3.6
License-File: LICENSE
Dynamic: author
Dynamic: author-email
Dynamic: classifier
Dynamic: description
Dynamic: description-content-type
Dynamic: home-page
Dynamic: license-file
Dynamic: requires-python
Dynamic: summary
